dsmcp/__init__.py
dsmcp/__main__.py
dsmcp/dcpbasic.py
dsmcp/dcpdev.py
dsmcp/app/__init__.py
dsmcp/app/_version.py
dsmcp/app/base.py
dsmcp/app/common.py
dsmcp/app/firmware.py
dsmcp/app/launcher.py
dsmcp/app/ressource.py
dsmcp/app/tracer.py
dsmcp/app/utils.py
dsmcp/app/cli/__init__.py
dsmcp/app/cli/base.py
dsmcp/app/cli/basic.py
dsmcp/app/cli/common.py
dsmcp/app/cli/dcpshell.py
dsmcp/app/cli/dev.py
dsmcp/app/gui/__init__.py
dsmcp/app/gui/base.py
dsmcp/app/gui/basic.py
dsmcp/app/gui/dev.py
dsmcp/app/gui/splashscreen.py
dsmcp/app/gui/ui_basicwindow.py
dsmcp/app/gui/dlg/__init__.py
dsmcp/app/gui/dlg/aboutboarddialog.py
dsmcp/app/gui/dlg/aboutdialog.py
dsmcp/app/gui/dlg/flashprogressdialog.py
dsmcp/app/gui/dlg/motormodedialog.py
dsmcp/app/gui/dlg/selectconnectiondialog.py
dsmcp/app/gui/dlg/sendfirmwaredialog.py
dsmcp/app/gui/dlg/ui_aboutboarddialog.py
dsmcp/app/gui/dlg/ui_aboutdialog.py
dsmcp/app/gui/dlg/ui_flashprogressdiaog.py
dsmcp/app/gui/dlg/ui_motormodedialog.py
dsmcp/app/gui/dlg/ui_selectconnectiondialog.py
dsmcp/app/gui/dlg/ui_sendfirmwaredialog.py
dsmcp/app/gui/res/__init__.py
dsmcp/app/gui/res/res_img.py
dsmcp/app/gui/widget/__init__.py
dsmcp/app/gui/widget/qactionbutton.py
dsmcp/app/gui/widget/qregister.py
dsmcp/app/gui/widget/qspeed.py
dsmcp/app/gui/widget/qspinboxregister.py
dsmcp/app/gui/widget/qsvgpanel.py
dsmcp/img/btn-dassym.png
dsmcp/img/btn-dassym.svg
dsmcp/img/btn-light.svg
dsmcp/img/btn-reverse.svg
dsmcp/img/layout-lipo.svg
dsmcp/img/layout-vantage-dark.svg
dsmcp/img/layout-vantage.svg
dsmcp-0.1.1.dist-info/LICENSE
dsmcp-0.1.1.dist-info/METADATA
dsmcp-0.1.1.dist-info/WHEEL
dsmcp-0.1.1.dist-info/top_level.txt
dsmcp-0.1.1.dist-info/RECORD
