Metadata-Version: 2.1
Name: dsmcp
Version: 0.1.1
Summary: The PyDapi2 library offers a Python implementation of the Dassym API version 2.
Home-page: https://github.com/dassym/dsmcp
Author: Fabrice Voillat
Author-email: dev@dassym.com
License: UNKNOWN
Platform: UNKNOWN
Classifier: Programming Language :: Python :: 3
Classifier: Operating System :: OS Independent
Requires-Python: >=3.8
Requires-Dist: lxml
Requires-Dist: pyserial
Requires-Dist: PyDapi2
Requires-Dist: chardet
